rusampling/.gitattributes
rusampling/__init__.py
rusampling/ru.py
rusampling/ru_libs.py
rusampling/vectorise.py
rusampling-0.0.5.dist-info/METADATA
rusampling-0.0.5.dist-info/WHEEL
rusampling-0.0.5.dist-info/licenses/LICENSE.md
rusampling-0.0.5.dist-info/RECORD
