Metadata-Version: 2.4
Name: rusampling
Version: 0.0.5
Summary: A Python package for Ratio-of-Uniforms sampling.
Project-URL: Homepage, https://github.com/lynnejewson/rusampling
Author-email: Lynne Jewson <lynne.jewson@gmail.com>
License-Expression: MIT
License-File: LICENSE.md
Classifier: Operating System :: OS Independent
Classifier: Programming Language :: Python :: 3
Requires-Python: >=3.9
Requires-Dist: matplotlib
Requires-Dist: numpy
Requires-Dist: scipy
